Metadata-Version: 1.1
Name: jmbo-superhero
Version: 0.1
Summary: Jmbo superhero application.  A content type that represents a bundle of HTML, JS and CSS on the filesystem.
Home-page: http://github.com/praekelt/jmbo-superhero
Author: Praekelt Foundation
Author-email: dev@praekelt.com
License: BSD
Platform: UNKNOWN
Classifier: Programming Language :: Python
Classifier: License :: OSI Approved :: BSD License
Classifier: Development Status :: 4 - Beta
Classifier: Operating System :: OS Independent
Classifier: Framework :: Django
Classifier: Intended Audience :: Developers
Classifier: Topic :: Internet :: WWW/HTTP :: Dynamic Content
